bgutils/__init__.py
bgutils/bgutils.py
bgutils/captchas.py
bgutils/csvUtil.py
bgutils/dtUtil.py
bgutils/fmtUtils.py
bgutils/ftpUtil.py
bgutils/iputils.py
bgutils/jsonUtils.py
bgutils/kafkautil.py
bgutils/logutil.py
bgutils/mongoUtil.py
bgutils/mysqlUtil.py
bgutils/photoUtil.py
bgutils/proxyUtils.py
bgutils/redisUtil.py
bgutils/sparkUtil.py
bgutils/twofa.py
bgutils/urlUtils.py
bgutils/entity/__init__.py
bgutils/entity/entHdd.py
bgutils/entity/entSftpFile.py
bgutils/entity/entUrlResult.py
bgutils/spider/BaseSpider.py
bgutils/spider/SpiderBook.py
bgutils/spider/SpiderCar.py
bgutils/spider/SpiderCourse.py
bgutils/spider/SpiderData.py
bgutils/spider/SpiderGame.py
bgutils/spider/SpiderGoods.py
bgutils/spider/SpiderHouse.py
bgutils/spider/SpiderJobs.py
bgutils/spider/SpiderMeishi.py
bgutils/spider/SpiderMusic.py
bgutils/spider/SpiderMusic1.py
bgutils/spider/SpiderMusic2.py
bgutils/spider/SpiderNews.py
bgutils/spider/SpiderStory.py
bgutils/spider/SpiderVideo.py
bgutils/spider/__init__.py
zbak/__init__.py
bgutils_hddly-1.1.104.dist-info/LICENSE
bgutils_hddly-1.1.104.dist-info/METADATA
bgutils_hddly-1.1.104.dist-info/WHEEL
bgutils_hddly-1.1.104.dist-info/top_level.txt
bgutils_hddly-1.1.104.dist-info/zip-safe
bgutils_hddly-1.1.104.dist-info/RECORD
