Metadata-Version: 2.1
Name: bgutils-hddly
Version: 1.1.104
Summary: bigdata utils.
Home-page: https://biglab.site
Author: hddly
Author-email: goodym@163.com
License: MIT
Classifier: Environment :: Web Environment
Classifier: Intended Audience :: Developers
Classifier: License :: OSI Approved :: MIT License
Classifier: Operating System :: MacOS
Classifier: Operating System :: Microsoft
Classifier: Operating System :: POSIX
Classifier: Operating System :: Unix
Classifier: Topic :: Software Development :: Libraries :: Python Modules
Classifier: Programming Language :: Python :: 3.8
Classifier: Programming Language :: Python :: 3.9
Classifier: Programming Language :: Python :: 3.10
Classifier: Programming Language :: Python :: 3.11
Classifier: Programming Language :: Python :: 3.12
License-File: LICENSE
Requires-Dist: pandas >=1.1.0
Requires-Dist: numpy >=1.14.0
Requires-Dist: paramiko >=2.11.0
Requires-Dist: pymongo >=3.11.1
Requires-Dist: requests >=2.26.0
Requires-Dist: seaborn >=0.13.2
Requires-Dist: moviepy >=1.0.3
Requires-Dist: kafka-python ==2.2.13
Requires-Dist: redis >=4.5.1
Requires-Dist: elasticsearch >=6.8.2
